lite_media_core/__init__.py
lite_media_core/mediaos.py
lite_media_core/rate.py
lite_media_core/resolution.py
lite_media_core/timecode.py
lite_media_core/_media_info/__init__.py
lite_media_core/_media_info/_base.py
lite_media_core/_media_info/_media_info_api.py
lite_media_core/_media_info/dll_resources/MediaInfo.dll
lite_media_core/_media_info/dll_resources/libmediainfo.0.dylib
lite_media_core/_media_info/dll_resources/libmediainfo.dylib
lite_media_core/_media_info/dll_resources/libmediainfo.so.0
lite_media_core/_media_info/dll_resources/libmms.so.0
lite_media_core/_media_info/dll_resources/libtinyxml2.so.6
lite_media_core/_media_info/dll_resources/libzen.so.0
lite_media_core/media/__init__.py
lite_media_core/media/_audio.py
lite_media_core/media/_embedded.py
lite_media_core/media/_image.py
lite_media_core/media/_image_media.py
lite_media_core/media/_media.py
lite_media_core/media/_video.py
lite_media_core/path_utils/__init__.py
lite_media_core/path_utils/mime_types.py
lite_media_core/path_utils/single_file.py
lite_media_core/path_utils/_resources/additional.mime.types
lite_media_core/path_utils/sequence/__init__.py
lite_media_core/path_utils/sequence/_formats.py
lite_media_core/path_utils/sequence/_frame_range.py
lite_media_core/path_utils/sequence/_sequence.py
lite_media_core/path_utils/sequence/_utils.py
lite_media_core-0.1.3.dist-info/licenses/LICENSE
lite_media_core-0.1.3.dist-info/METADATA
lite_media_core-0.1.3.dist-info/WHEEL
lite_media_core-0.1.3.dist-info/top_level.txt
lite_media_core-0.1.3.dist-info/RECORD
