Metadata-Version: 2.4
Name: lite_media_core
Version: 0.1.3
Summary: A lightweight yet powerful media framework for developers.
License: GPL-3.0-or-later
Project-URL: Homepage, https://github.com/rdelillo/lite_media_core
Requires-Python: >=3.6
License-File: LICENSE
Requires-Dist: timecode
Requires-Dist: fileseq==1.8.1
Requires-Dist: pymediainfo
Provides-Extra: testing
Requires-Dist: pytest; extra == "testing"
Requires-Dist: pytest-cov; extra == "testing"
Requires-Dist: mock; extra == "testing"
Provides-Extra: embedded
Requires-Dist: requests; extra == "embedded"
Requires-Dist: validators; extra == "embedded"
Requires-Dist: yt-dlp; extra == "embedded"
Provides-Extra: lint
Requires-Dist: ruff; extra == "lint"
Dynamic: license-file
